{"users":[{"voice":200000000,"requiredXp":1928230,"currentXp":1809900,"avatar_url":"https://cdn.discordapp.com/avatars/668075003610398721/ff65440a64a1817215baba4aa6dacfd9.png","level":616,"name":"KCplayerGessler_","voicePlace":0,"progress":0.93,"textPlace":0,"text":200000000},{"voice":0,"requiredXp":150,"currentXp":0,"avatar_url":"https://cdn.discordapp.com/avatars/827572027685863425/d2b1924f6035f4c99600ea95360eee8b.png","level":0,"name":"Kokscraft Statystyki","voicePlace":2,"progress":0,"textPlace":1,"text":0},{"voice":0,"requiredXp":150,"currentXp":0,"avatar_url":"https://cdn.discordapp.com/avatars/172002275412279296/43fc1879641f6239d6e4038eaa7dabbc.png","level":0,"name":"Tatsu","voicePlace":1,"progress":0,"textPlace":2,"text":0}],"guildInfo":{"roles":[],"name":"testy"}}