{"users":[{"voice":761546,"requiredXp":30445,"currentXp":11617,"avatar_url":"https://cdn.discordapp.com/avatars/201430944748404736/a_d67d1814f20a4b57b08da4c11794142c.gif","level":73,"name":"pan_truskawka045","voicePlace":0,"progress":0.38,"textPlace":0,"text":27521},{"voice":5493,"requiredXp":1150,"currentXp":338,"avatar_url":"https://cdn.discordapp.com/embed/avatars/0.png","level":10,"name":"Witam","voicePlace":1,"progress":0.29,"textPlace":4,"text":20},{"voice":0,"requiredXp":150,"currentXp":70,"avatar_url":"https://cdn.discordapp.com/avatars/716208230384140418/a73c5e00970621b5fdff75879b32a7ef.png","level":0,"name":".stuwa","voicePlace":7,"progress":0.46,"textPlace":1,"text":70},{"voice":0,"requiredXp":150,"currentXp":57,"avatar_url":"https://cdn.discordapp.com/avatars/600945177259016192/a_e25eada6fa6b8221c24acecea17f9939.gif","level":0,"name":"Mitysia","voicePlace":2,"progress":0.38,"textPlace":2,"text":57},{"voice":0,"requiredXp":150,"currentXp":35,"avatar_url":"https://cdn.discordapp.com/avatars/753233639583514674/a_06371a9721fcbf0741010c7d0aa556e1.gif","level":0,"name":"viv.","voicePlace":6,"progress":0.23,"textPlace":3,"text":35},{"voice":0,"requiredXp":150,"currentXp":17,"avatar_url":"https://cdn.discordapp.com/avatars/305104947954057217/a_cefb09c85cceab227fe81f3d3ecb1cf2.gif","level":0,"name":"Skay","voicePlace":4,"progress":0.11,"textPlace":5,"text":17},{"voice":0,"requiredXp":150,"currentXp":16,"avatar_url":"https://cdn.discordapp.com/avatars/716338152217772083/5aee27efecb68d8323fe5bbe7f823bc3.png","level":0,"name":"klauudx","voicePlace":8,"progress":0.1,"textPlace":6,"text":16},{"voice":0,"requiredXp":150,"currentXp":11,"avatar_url":"https://cdn.discordapp.com/avatars/417012054248128512/a_855bef111bfbdbd52c34dbae67f05e67.gif","level":0,"name":"𝓦𝓸𝓳𝓬𝓲𝓮𝓬𝓱 ❤","voicePlace":5,"progress":0.07,"textPlace":7,"text":11},{"voice":0,"requiredXp":150,"currentXp":0,"avatar_url":"https://cdn.discordapp.com/avatars/509027420909862933/29c3515d869738cab9304be510c990b2.png","level":0,"name":"ThunerS","voicePlace":9,"progress":0,"textPlace":8,"text":0},{"voice":0,"requiredXp":150,"currentXp":0,"avatar_url":"https://cdn.discordapp.com/avatars/822139129927041035/85cc7e975dd38f7d0ed5d9fa8782e8d9.png","level":0,"name":"Norbert gierczak","voicePlace":3,"progress":0,"textPlace":9,"text":0}],"guildInfo":{"roles":[],"name":"Sokowy Swiat","iconUrl":"https://cdn.discordapp.com/icons/827651173544493116/7d70fb72445ecce4c5058d5e34fb7e9a.png"}}